{
  "clients": [
    {
      "id": 1,
      "name": "John Doe",
      "idNumber": "1234567890",
      "gender": "Male",
      "birthday": "1990-01-01",
      "phone": "123-456-7890",
      "mobile": "098-765-4321",
      "address": "1456 Maple Avenue, Elmwood, IL 60712",
      "note": "Leave package behind the garden gnome."
    },

    {
      "id": 2,
      "name": "Jane Smith",
      "idNumber": "2345678901",
      "gender": "female",
      "birthday": "1985-05-15",
      "phone": "234-567-8901",
      "mobile": "097-654-3210",
      "address": "2028 Starlight Drive, Crescent City, CA 95531",
      "note": "Buzz apartment 401 on the intercom"
    },
    {
      "id": 3,
      "name": "Michael Johnson",
      "idNumber": "3456789012",
      "gender": "male",
      "birthday": "1988-11-30",
      "phone": "345-678-9012",
      "mobile": "096-543-2109",
      "address": "7334 Pine Road, Frostburg, MD 21532",
      "note": "Gate code is #4321, beware of the dog"
    },
    {
      "id": 4,
      "name": "Emily Williams",
      "idNumber": "4567890123",
      "gender": "female",
      "birthday": "1987-03-20",
      "phone": "456-789-0123",
      "mobile": "095-432-1098",
      "address": "8862 Old Dairy Lane, Southridge, VT 05403",
      "note": "Deliveries only between 10 AM and 2 PM"
    },
    {
      "id": 5,
      "name": "Daniel Brown",
      "idNumber": "5678901234",
      "gender": "male",
      "birthday": "1992-08-05",
      "phone": "567-890-1234",
      "mobile": "094-321-0987",
      "address": "4407 Winding Way, Providence, RI 02908",
      "note": "Leave parcels at the back door"
    },
    {
      "id": 6,
      "name": "Olivia Garcia",
      "idNumber": "6789012345",
      "gender": "female",
      "birthday": "1986-12-10",
      "phone": "678-901-2345",
      "mobile": "093-210-9876",
      "address": "3189 Sunset Boulevard, Oceanview, FL 33140",
      "note": "Front door hidden behind large palm tree"
    },
    {
      "id": 7,
      "name": "William Martinez",
      "idNumber": "7890123456",
      "gender": "male",
      "birthday": "1995-04-25",
      "phone": "789-012-3456",
      "mobile": "092-109-8765",
      "address": "1592 Eagle Street, Summit, OK 73018",
      "note": "If no answer, leave with neighbor at 1600."
    },
    {
      "id": 8,
      "name": "Sophia Hernandez",
      "idNumber": "8901234567",
      "gender": "female",
      "birthday": "1989-10-15",
      "phone": "890-123-4567",
      "mobile": "091-098-7654",
      "address": "4905 Whispering Pines Drive, Cloudtown, TX 78373",
      "note": "The driveway sensor will alert when you arrive"
    },
    {
      "id": 9,
      "name": "Matthew Taylor",
      "idNumber": "9012345678",
      "gender": "male",
      "birthday": "1991-06-20",
      "phone": "901-234-5678",
      "mobile": "090-987-6543",
      "address": "7201 Highland Road, Stonybrook, MN 55902",
      "note": "Place under the porch swing"
    },
    {
      "id": 10,
      "name": "Emma Rodriguez",
      "idNumber": "0123456789",
      "gender": "female",
      "birthday": "1994-02-28",
      "phone": "012-345-6789",
      "mobile": "099-876-5432",
      "address": "2187 Liberty Ave, Freedom City, NV 89501",
      "note": "Security will assist with entry"
    },
    {
      "id": 11,
      "name": "James Brown",
      "idNumber": "9876543210",
      "gender": "male",
      "birthday": "1984-07-12",
      "phone": "987-654-3210",
      "mobile": "098-765-4321",
      "address": "6223 Avalon Blvd, New Springfield, MA 01104",
      "note": "Do not knock; baby sleeping"
    },
    {
      "id": 12,
      "name": "Ava Wilson",
      "idNumber": "8765432109",
      "gender": "female",
      "birthday": "1993-11-18",
      "phone": "876-543-2109",
      "mobile": "097-654-3210",
      "address": "303 Eastwood Circle, Maplewood, NJ 07040",
      "note": "Use side entrance on the left of the house"
    },
    {
      "id": 13,
      "name": "Alexander Thomas",
      "idNumber": "7654321098",
      "gender": "male",
      "birthday": "1996-01-05",
      "phone": "765-432-1098",
      "mobile": "096-543-2109",
      "address": "9890 Cherry Blossom Way, Lakeview, OR 97630",
      "note": "Place inside the screen door"
    },
    {
      "id": 14,
      "name": "Mia Anderson",
      "idNumber": "6543210987",
      "gender": "female",
      "birthday": "1983-09-30",
      "phone": "654-321-0987",
      "mobile": "095-432-1098",
      "address": "467 Riverside Drive, River City, IA 50613",
      "note": "Parcel can be left with concierge"
    },
    {
      "id": 15,
      "name": "Ethan Garcia",
      "idNumber": "5432109876",
      "gender": "male",
      "birthday": "1990-02-15",
      "phone": "543-210-9876",
      "mobile": "094-321-0987",
      "address": "7554 Orchard Lane, Cedar Mill, KY 41015",
      "note": "Gate sticks, please push hard"
    },
    {
      "id": 16,
      "name": "Charlotte Jackson",
      "idNumber": "4321098765",
      "gender": "female",
      "birthday": "1987-05-22",
      "phone": "432-109-8765",
      "mobile": "093-210-9876",
      "address": "88 Queen Elizabeth Drive, Kingsville, MO 64085",
      "note": "Leave in the shed if raining"
    },
    {
      "id": 17,
      "name": "Noah Taylor",
      "idNumber": "3210987654",
      "gender": "male",
      "birthday": "1995-08-08",
      "phone": "321-098-7654",
      "mobile": "092-109-8765",
      "address": "3367 South Main Street, Midvale, DE 19958",
      "note": "Park in driveway during delivery"
    },
    {
      "id": 18,
      "name": "Isabella Brown",
      "idNumber": "2109876543",
      "gender": "female",
      "birthday": "1988-12-01",
      "phone": "210-987-6543",
      "mobile": "091-098-7654",
      "address": "1924 Juniper Lane, Misty Ridge, TN 37402",
      "note": "If no answer, leave behind the flower pots."
    },
    {
      "id": 19,
      "name": "Liam Hernandez",
      "idNumber": "1098765432",
      "gender": "male",
      "birthday": "1993-03-25",
      "phone": "109-876-5432",
      "mobile": "090-987-6543",
      "address": "310 Whisper Creek Court, Wildwood, CO 80401",
      "note": "Second driveway on the left"
    },
    {
      "id": 20,
      "name": "Evelyn Martinez",
      "idNumber": "0987654321",
      "gender": "female",
      "birthday": "1986-06-17",
      "phone": "098-765-4321",
      "mobile": "099-876-5432",
      "address": "1701 Lighthouse Point, Beacon End, ME 04005",
      "note": "Please deliver before 5 pm; gate locks automatically."
    }
  ]
}
